<annotation>
	<folder>Oriental</folder>
	<filename>Oriental (289).jpg</filename>
	<path>E:\1_31\Oriental\Oriental (289).jpg</path>
	<source>
		<database>Unknown</database>
	</source>
	<size>
		<width>800</width>
		<height>418</height>
		<depth>3</depth>
	</size>
	<segmented>0</segmented>
	<object>
		<name>Oriental</name>
		<pose>Unspecified</pose>
		<truncated>0</truncated>
		<difficult>0</difficult>
		<bndbox>
			<xmin>150</xmin>
			<ymin>26</ymin>
			<xmax>205</xmax>
			<ymax>357</ymax>
		</bndbox>
	</object>
</annotation>
