<annotation>
	<folder>SL</folder>
	<filename>SL (257).jpg</filename>
	<path>E:\yxr_data\SL\SL (257).jpg</path>
	<source>
		<database>Unknown</database>
	</source>
	<size>
		<width>576</width>
		<height>768</height>
		<depth>3</depth>
	</size>
	<segmented>0</segmented>
	<object>
		<name>SL</name>
		<pose>Unspecified</pose>
		<truncated>0</truncated>
		<difficult>0</difficult>
		<bndbox>
			<xmin>189</xmin>
			<ymin>252</ymin>
			<xmax>359</xmax>
			<ymax>666</ymax>
		</bndbox>
	</object>
</annotation>
