<annotation>
	<folder>Teng</folder>
	<filename>Teng (30).jpg</filename>
	<path>E:\1_31\Teng\Teng (30).jpg</path>
	<source>
		<database>Unknown</database>
	</source>
	<size>
		<width>800</width>
		<height>534</height>
		<depth>3</depth>
	</size>
	<segmented>0</segmented>
	<object>
		<name>Teng</name>
		<pose>Unspecified</pose>
		<truncated>0</truncated>
		<difficult>0</difficult>
		<bndbox>
			<xmin>93</xmin>
			<ymin>57</ymin>
			<xmax>511</xmax>
			<ymax>401</ymax>
		</bndbox>
	</object>
</annotation>
