<annotation>
	<folder>ThreePagoda</folder>
	<filename>ThreePagoda (334).jpg</filename>
	<path>E:\1_31\ThreePagoda\ThreePagoda (334).jpg</path>
	<source>
		<database>Unknown</database>
	</source>
	<size>
		<width>800</width>
		<height>514</height>
		<depth>3</depth>
	</size>
	<segmented>0</segmented>
	<object>
		<name>ThreePagoda</name>
		<pose>Unspecified</pose>
		<truncated>0</truncated>
		<difficult>0</difficult>
		<bndbox>
			<xmin>418</xmin>
			<ymin>59</ymin>
			<xmax>461</xmax>
			<ymax>234</ymax>
		</bndbox>
	</object>
</annotation>
